cli/__init__.py
cli/argsParser.py
cli/commandLineEntryPoint.py
client/__init__.py
client/cliClient.py
client/clientConfig.py
cmnSys/__init__.py
cmnSys/action.py
cmnSys/directoryFinder.py
cmnSys/responseCode.py
cmnSys/simpleConfig.py
cmnUtils/__init__.py
cmnUtils/configManager.py
cmnUtils/dateUtils.py
cmnUtils/safeOpen.py
networking/__init__.py
networking/tcpClient.py
networking/tcpServer.py
networking/packets/__init__.py
networking/packets/packet.py
server/__init__.py
server/adjacencyList.py
server/adjacencyMatrix.py
server/adjacentEmployeeManager.py
server/cliServer.py
server/employeeInfoMap.py
server/schedule.py
server/serverConfig.py
server/serverQueryManager.py
Desk_Buddies-0.0.1.dist-info/METADATA
Desk_Buddies-0.0.1.dist-info/WHEEL
Desk_Buddies-0.0.1.dist-info/entry_points.txt
Desk_Buddies-0.0.1.dist-info/top_level.txt
Desk_Buddies-0.0.1.dist-info/RECORD
